[
    {
        "original_title": "Strul",
        "id": 1210794
    },
    {
        "original_title": "Pleasure",
        "id": 592695
    },
    {
        "original_title": "Canceled",
        "id": 1070535
    },
    {
        "original_title": "Lust och f\u00e4gring stor",
        "id": 27098
    },
    {
        "original_title": "Karusell",
        "id": 1058078
    },
    {
        "original_title": "Lilja 4-Ever",
        "id": 12093
    },
    {
        "original_title": "91:an Karlsson",
        "id": 146451
    },
    {
        "original_title": "Kyss mig",
        "id": 71325
    },
    {
        "original_title": "Avgrunden",
        "id": 1053544
    },
    {
        "original_title": "Strul",
        "id": 35327
    },
    {
        "original_title": "Tabu",
        "id": 135348
    },
    {
        "original_title": "Joker",
        "id": 146486
    },
    {
        "original_title": "Flickan som lekte med elden",
        "id": 24253
    },
    {
        "original_title": "En man som heter Ove",
        "id": 348678
    },
    {
        "original_title": "Sommarnattens leende",
        "id": 11700
    },
    {
        "original_title": "Pippi L\u00e5ngstrump",
        "id": 12097
    },
    {
        "original_title": "Tack och f\u00f6rl\u00e5t",
        "id": 1211199
    },
    {
        "original_title": "G\u00f6ta Kanal eller Vem drog ur proppen?",
        "id": 22435
    },
    {
        "original_title": "Konferensen",
        "id": 1161048
    },
    {
        "original_title": "Offret",
        "id": 24657
    },
    {
        "original_title": "Svart krabba",
        "id": 760868
    },
    {
        "original_title": "Smultronst\u00e4llet",
        "id": 614
    },
    {
        "original_title": "XXL",
        "id": 1229831
    },
    {
        "original_title": "Ronja R\u00f6vardotter",
        "id": 271
    },
    {
        "original_title": "Vinterviken",
        "id": 726916
    },
    {
        "original_title": "Quick",
        "id": 606146
    },
    {
        "original_title": "Noll tolerans",
        "id": 21072
    },
    {
        "original_title": "Fanny och Alexander",
        "id": 5961
    },
    {
        "original_title": "Falsk som vatten",
        "id": 105737
    },
    {
        "original_title": "Den tredje v\u00e5gen",
        "id": 21041
    },
    {
        "original_title": "Anita",
        "id": 47397
    },
    {
        "original_title": "Luftslottet som spr\u00e4ngdes",
        "id": 33613
    },
    {
        "original_title": "Underjordens hemlighet",
        "id": 229509
    },
    {
        "original_title": "Snabba cash - Livet deluxe",
        "id": 196032
    },
    {
        "original_title": "J\u00f6nssonligan dyker upp igen",
        "id": 22192
    },
    {
        "original_title": "Det sjunde inseglet",
        "id": 490
    },
    {
        "original_title": "N\u00e4ra livet",
        "id": 60899
    },
    {
        "original_title": "S\u00e4llskapsresan II - Snowroller",
        "id": 19181
    },
    {
        "original_title": "L\u00e5t den r\u00e4tte komma in",
        "id": 13310
    },
    {
        "original_title": "Hypnosen",
        "id": 1005972
    },
    {
        "original_title": "Mitt liv som hund",
        "id": 8816
    },
    {
        "original_title": "En del av dig",
        "id": 1127108
    },
    {
        "original_title": "Emil i L\u00f6nneberga",
        "id": 11945
    },
    {
        "original_title": "Vi \u00e4r b\u00e4st!",
        "id": 191294
    },
    {
        "original_title": "Livvakterna",
        "id": 21040
    },
    {
        "original_title": "Kenny Begins",
        "id": 21013
    },
    {
        "original_title": "Fucking \u00c5m\u00e5l",
        "id": 11634
    },
    {
        "original_title": "Koko-di Koko-da",
        "id": 565373
    },
    {
        "original_title": "And the King Said, What a Fantastic Machine",
        "id": 1058652
    },
    {
        "original_title": "Babblarna - Bara p\u00e5 Youtube Filmen",
        "id": 471628
    },
    {
        "original_title": "M\u00e4n som hatar kvinnor",
        "id": 15472
    },
    {
        "original_title": "Gr\u00e4ns",
        "id": 517839
    },
    {
        "original_title": "Den blomstertid nu kommer",
        "id": 518502
    },
    {
        "original_title": "Ur k\u00e4rlekens spr\u00e5k",
        "id": 220436
    },
    {
        "original_title": "Breaking Surface",
        "id": 616803
    },
    {
        "original_title": "Livet \u00e4r en schlager",
        "id": 21842
    },
    {
        "original_title": "UFO Sweden",
        "id": 916401
    },
    {
        "original_title": "Hammarskj\u00f6ld",
        "id": 1084145
    },
    {
        "original_title": "Nybyggarna",
        "id": 42488
    },
    {
        "original_title": "Pippi L\u00e5ngstrump p\u00e5 de sju haven",
        "id": 12127
    },
    {
        "original_title": "Om det o\u00e4ndliga",
        "id": 348672
    },
    {
        "original_title": "Jag \u00e4r nyfiken - en film i gult",
        "id": 42695
    },
    {
        "original_title": "Feed",
        "id": 1015936
    },
    {
        "original_title": "Alla vi barn i Bullerbyn",
        "id": 21394
    },
    {
        "original_title": "P\u00e5 rymmen med Pippi L\u00e5ngstrump",
        "id": 11626
    },
    {
        "original_title": "Rum 213",
        "id": 427337
    },
    {
        "original_title": "Viskningar och rop",
        "id": 10238
    },
    {
        "original_title": "Aniara",
        "id": 496743
    },
    {
        "original_title": "Tillsammans",
        "id": 742
    },
    {
        "original_title": "V\u00e4rldens vackraste pojke",
        "id": 730028
    },
    {
        "original_title": "Ondskan",
        "id": 11197
    },
    {
        "original_title": "Turist",
        "id": 265189
    },
    {
        "original_title": "Medan porten var st\u00e4ngd",
        "id": 223315
    },
    {
        "original_title": "Draug",
        "id": 421285
    },
    {
        "original_title": "Inkr\u00e4ktarna",
        "id": 220438
    },
    {
        "original_title": "G\u00f6ta Kanal 2 - kanalkampen",
        "id": 22436
    },
    {
        "original_title": "Emil och griseknoen",
        "id": 11947
    },
    {
        "original_title": "L\u00e4rjungen",
        "id": 218850
    },
    {
        "original_title": "St\u00f6ld",
        "id": 1019317
    },
    {
        "original_title": "Den goda viljan",
        "id": 41764
    },
    {
        "original_title": "De ofrivilliga",
        "id": 8927
    },
    {
        "original_title": "Heartbreak Hotel",
        "id": 2180
    },
    {
        "original_title": "Greta",
        "id": 728123
    },
    {
        "original_title": "Vargtimmen",
        "id": 18333
    },
    {
        "original_title": "En passion",
        "id": 42602
    },
    {
        "original_title": "Agnes Cecilia - En s\u00e4llsam historia",
        "id": 229177
    },
    {
        "original_title": "Mig \u00e4ger ingen",
        "id": 199740
    },
    {
        "original_title": "Innan Frosten",
        "id": 221868
    },
    {
        "original_title": "Studio Sex",
        "id": 118279
    },
    {
        "original_title": "Kvinnors v\u00e4ntan",
        "id": 69544
    },
    {
        "original_title": "Persona",
        "id": 797
    },
    {
        "original_title": "Terje Vigen",
        "id": 108017
    },
    {
        "original_title": "Jungfruk\u00e4llan",
        "id": 11656
    },
    {
        "original_title": "S\u00e5nger fr\u00e5n andra v\u00e5ningen",
        "id": 34070
    },
    {
        "original_title": "One More Time",
        "id": 1100962
    },
    {
        "original_title": "Stockholm \u00d6stra",
        "id": 86983
    },
    {
        "original_title": "Snapphanar",
        "id": 225843
    },
    {
        "original_title": "Pleasure",
        "id": 199702
    },
    {
        "original_title": "Sameblod",
        "id": 408435
    },
    {
        "original_title": "Maria Larssons eviga \u00f6gonblick",
        "id": 17077
    }
]